cvpartner/__init__.py
cvpartner/cvpartner.py
cvpartnerpy-0.0.4.dist-info/LICENSE.txt
cvpartnerpy-0.0.4.dist-info/METADATA
cvpartnerpy-0.0.4.dist-info/WHEEL
cvpartnerpy-0.0.4.dist-info/top_level.txt
cvpartnerpy-0.0.4.dist-info/RECORD
