Metadata-Version: 2.1
Name: cvpartnerpy
Version: 0.0.4
Summary: A python package for scraping cvpartner api
Home-page: https://github.com/peakBreaker/cvpartnerpy
Author: Anders L. Hurum
Author-email: andershurum@gmail.com
License: All rights reserved
Platform: UNKNOWN
Classifier: Programming Language :: Python
Classifier: Programming Language :: Python :: 3
Classifier: Programming Language :: Python :: 3.6
Requires-Python: >=3.5.0
Requires-Dist: certifi (==2020.11.8)
Requires-Dist: chardet (==3.0.4)
Requires-Dist: idna (==2.10)
Requires-Dist: requests (==2.25.0)
Requires-Dist: urllib3 (==1.26.2)
